[{"name":"$getVolume","description":"gets the guild player volume/loudness","version":"1.0.3","brackets":false,"unwrap":true,"args":[{"name":"Guild ID","description":"The ID of the guild","rest":false,"required":true,"type":"Guild"}],"output":["String"],"category":"Controls"},{"name":"$pause","description":"Pauses the guild player","version":"1.0.0","brackets":false,"unwrap":true,"args":[{"name":"Guild ID","description":"The ID of the guild","rest":false,"required":true,"type":"Guild"}],"output":["String"],"category":"Controls"},{"name":"$previousExists","description":"Check whether a previous track exists in the player queue.","version":"1.0.2","brackets":false,"unwrap":true,"args":[{"name":"Guild ID","description":"The ID of the guild to check the player for.","rest":false,"required":true,"type":"Guild"}],"output":["Boolean"],"category":"Controls"},{"name":"$previousTrack","description":"Goes to a previous track in the queue (if one exists)","version":"1.0.0","brackets":false,"unwrap":true,"args":[{"name":"Guild ID","description":"The ID of the guild","rest":false,"required":true,"type":"Guild"}],"output":["String"],"category":"Controls"},{"name":"$resume","description":"Resumes the track in the guild player","version":"1.0.0","brackets":false,"unwrap":true,"args":[{"name":"Guild ID","description":"The ID of the guild","rest":false,"required":true,"type":"Guild"}],"output":["String"],"category":"Controls"},{"name":"$setVolume","description":"Sets the guild player volume/loudness (recomended limit:200) ","version":"1.0.1","brackets":true,"unwrap":true,"args":[{"name":"Guild ID","description":"The ID of the guild","rest":false,"required":true,"type":"Guild"},{"name":"volume","description":"volume","type":"Number","required":true,"rest":false}],"output":["String"],"category":"Controls"},{"name":"$skipExists","description":"Check whether the next track exists in the player queue.","version":"1.0.2","brackets":false,"unwrap":true,"args":[{"name":"Guild ID","description":"The ID of the guild to check the player for.","rest":false,"required":true,"type":"Guild"}],"output":["Boolean"],"category":"Controls"},{"name":"$skipTrack","description":"Skips the track in the guild player","version":"1.0.0","brackets":false,"unwrap":true,"args":[{"name":"Guild ID","description":"The ID of the guild","rest":false,"required":true,"type":"Guild"}],"output":["String"],"category":"Controls"},{"name":"$addFilter","description":"Filters Test Setup","version":"1.0.3","brackets":false,"unwrap":true,"args":[{"name":"Guild ID","description":"The ID of the guild ","rest":false,"required":true,"type":"Guild"},{"name":"Filter","description":"The Filter to apply","rest":false,"required":true,"type":"String"}],"output":["Boolean"],"category":"Filters"},{"name":"$addNode","description":"Adds a new Lavalink node.","version":"1.0.2","brackets":true,"unwrap":true,"args":[{"name":"Name","description":"The name of the node to add to the player","rest":false,"required":true,"type":"String"},{"name":"Authentication","description":"The password to authenticate the node","rest":false,"required":true,"type":"String"},{"name":"Host","description":"The hostname or IP of the Lavalink server","rest":false,"required":true,"type":"String"},{"name":"Port","description":"The port Lavalink is running on","rest":false,"required":true,"type":"Number"},{"name":"Secure","description":"Whether or not the node is secure.","rest":false,"required":true,"type":"Boolean"}],"output":["Boolean"],"category":"Node"},{"name":"$getNodes","description":"Gets the lavalink nodes.","version":"1.0.2","brackets":false,"unwrap":true,"experimental":true,"args":[{"name":"Guild ID","description":"The ID of the guild of the player to.","rest":false,"required":true,"type":"Guild"}],"output":["Json"],"category":"Node"},{"name":"$nodeExists","description":"Checks if a node exists from the name.","version":"1.0.2","brackets":false,"unwrap":true,"args":[{"name":"Name","description":"The name of the node","rest":false,"required":true,"type":"String"}],"output":["Boolean"],"category":"Node"},{"name":"$removeNode","description":"removes a Lavalink node.","version":"1.0.2","brackets":true,"unwrap":true,"args":[{"name":"Name","description":"The name of the node to remove from the player","rest":false,"required":true,"type":"String"},{"name":"Reason","description":"The reason of the removal of the node","rest":false,"required":true,"type":"String"}],"output":["Boolean"],"category":"Node"},{"name":"$createPlayer","description":"Creates a new music player in the given guild.","version":"1.0.0","brackets":true,"unwrap":true,"args":[{"name":"Guild ID","description":"The ID of the guild to create the player to.","rest":false,"required":true,"type":"Guild"},{"name":"Voice ID","description":"The voice channel to connect to.","type":"Channel","required":true,"rest":false},{"name":"Text ID","description":"The text channel to send messages to.","rest":false,"type":"TextChannel"}],"output":["Boolean"],"category":"Player"},{"name":"$destroyPlayer","description":"Destroys a music player in the given guild.","version":"1.0.0","brackets":false,"unwrap":true,"args":[{"name":"Guild ID","description":"The ID of the guild to create the player to.","rest":false,"required":true,"type":"Guild"}],"output":["Boolean"],"category":"Player"},{"name":"$hasPlayer","description":"Check whether the given guild has a player created.","version":"1.0.0","brackets":false,"unwrap":true,"args":[{"name":"Guild ID","description":"The ID of the guild to create the player to.","rest":false,"required":true,"type":"Guild"}],"output":["Boolean"],"category":"Player"},{"name":"$playerElapsedTime","aliases":["$elapsedTime"],"description":"Returns the elapsed time of the current song in milliseconds.","version":"1.0.0","brackets":false,"unwrap":true,"args":[{"name":"Guild ID","description":"The ID of the guild ","rest":false,"required":true,"type":"Guild"}],"output":["String"],"category":"Player"},{"name":"$playerTextID","description":"gets the players text channel id.","version":"1.0.0","brackets":false,"unwrap":true,"args":[{"name":"Guild ID","description":"The ID of the guild get the player ID from.","rest":false,"required":true,"type":"Guild"}],"output":["TextChannel"],"category":"Player"},{"name":"$searchEngine","description":"Sets the player's search engine.","version":"1.1.0","brackets":true,"unwrap":true,"args":[{"name":"Engine","description":"The engine to use (ytsearch, scsearch, spsearch).","type":"String","required":true,"rest":false}],"output":["Json"],"category":"Player"},{"name":"$addTrack","description":"Adds a track into the guild player to listen to.","version":"1.0.0","brackets":true,"unwrap":true,"args":[{"name":"Guild ID","description":"The ID of the guild to create the player to.","rest":false,"required":true,"type":"Guild"},{"name":"Query","description":"Search query.","rest":false,"required":true,"type":"String"}],"output":["String"],"category":"Queue"},{"name":"$clearQueue","description":"Clears the queue/all tracks from the guild player","version":"1.0.0","brackets":false,"unwrap":true,"args":[{"name":"Guild ID","description":"The ID of the guild ","rest":false,"required":true,"type":"Guild"}],"output":["String"],"category":"Queue"},{"name":"$currentTrackInfo","description":"Gets info on the current track.","version":"1.0.0","brackets":false,"unwrap":true,"args":[{"name":"Guild ID","description":"The ID of the guild","rest":false,"required":true,"type":"Guild"}],"output":["Json"],"category":"Queue"},{"name":"$isPaused","description":"Check whether the given guild player is paused.","version":"1.0.0","brackets":false,"unwrap":true,"args":[{"name":"Guild ID","description":"The ID of the guild to create the player to.","rest":false,"required":true,"type":"Guild"}],"output":["Boolean"],"category":"Queue"},{"name":"$queue","description":"displays the queue/all tracks from the guild player","version":"1.0.3","brackets":false,"unwrap":true,"args":[{"name":"Guild ID","description":"The ID of the guild ","rest":false,"required":true,"type":"Guild"}],"output":["Json"],"category":"Queue"},{"name":"$queueHistory","description":"Displays the history of previously played tracks from the guild player.","version":"1.1.0","brackets":false,"experimental":true,"unwrap":true,"args":[{"name":"Guild ID","description":"The ID of the guild","rest":false,"required":true,"type":"Guild"}],"output":["Json"],"category":"Queue"},{"name":"$queueLength","description":"displays the queue length in the guild player","version":"1.0.0","brackets":false,"unwrap":true,"args":[{"name":"Guild ID","description":"The ID of the guild ","rest":false,"required":true,"type":"Guild"}],"output":["String"],"category":"Queue"},{"name":"$removeTrack","description":"Removes a track from the guild player","version":"1.0.0","brackets":true,"unwrap":true,"args":[{"name":"Guild ID","description":"The ID of the guild","rest":false,"required":true,"type":"Guild"},{"name":"Position","description":"track position","type":"Number","required":true,"rest":false}],"output":["String"],"category":"Queue"},{"name":"$searchTrack","description":"Searches for tracks in the guild and returns results.","version":"1.0.3","brackets":true,"unwrap":true,"args":[{"name":"Guild ID","description":"The ID of the guild to search in.","rest":false,"required":true,"type":"Guild"},{"name":"Query","description":"The search query.","rest":false,"required":true,"type":"String"},{"name":"Limit","description":"The maximum number of results to return.","rest":false,"type":"Number"}],"output":["Json"],"category":"Queue"},{"name":"$trackInfoOf","description":"Gets info on a track from a guild player","version":"1.0.0","brackets":true,"unwrap":true,"args":[{"name":"Guild ID","description":"The ID of the guild","rest":false,"required":true,"type":"Guild"},{"name":"Position","description":"The track position/index to fetch from.","rest":false,"required":true,"type":"Number"}],"output":["Json"],"category":"Queue"}]